ondine/__init__.py
ondine/adapters/__init__.py
ondine/adapters/checkpoint_storage.py
ondine/adapters/data_io.py
ondine/adapters/llm_client.py
ondine/adapters/provider_registry.py
ondine/api/__init__.py
ondine/api/dataset_processor.py
ondine/api/health_check.py
ondine/api/pipeline.py
ondine/api/pipeline_builder.py
ondine/api/pipeline_composer.py
ondine/api/quick.py
ondine/cli/__init__.py
ondine/cli/main.py
ondine/config/__init__.py
ondine/config/config_loader.py
ondine/core/__init__.py
ondine/core/error_handler.py
ondine/core/exceptions.py
ondine/core/models.py
ondine/core/specifications.py
ondine/integrations/__init__.py
ondine/integrations/airflow.py
ondine/integrations/prefect.py
ondine/observability/__init__.py
ondine/observability/base.py
ondine/observability/dispatcher.py
ondine/observability/events.py
ondine/observability/llamaindex_handlers.py
ondine/observability/observer.py
ondine/observability/registry.py
ondine/observability/sanitizer.py
ondine/observability/tracer.py
ondine/observability/observers/__init__.py
ondine/observability/observers/langfuse_observer.py
ondine/observability/observers/logging_observer.py
ondine/observability/observers/opentelemetry_observer.py
ondine/orchestration/__init__.py
ondine/orchestration/async_executor.py
ondine/orchestration/execution_context.py
ondine/orchestration/execution_strategy.py
ondine/orchestration/observers.py
ondine/orchestration/pipeline_executor.py
ondine/orchestration/progress_tracker.py
ondine/orchestration/state_manager.py
ondine/orchestration/streaming_executor.py
ondine/orchestration/sync_executor.py
ondine/stages/__init__.py
ondine/stages/batch_aggregator_stage.py
ondine/stages/batch_disaggregator_stage.py
ondine/stages/data_loader_stage.py
ondine/stages/llm_invocation_stage.py
ondine/stages/multi_run_stage.py
ondine/stages/parser_factory.py
ondine/stages/pipeline_stage.py
ondine/stages/prompt_formatter_stage.py
ondine/stages/response_parser_stage.py
ondine/stages/result_writer_stage.py
ondine-1.3.3.dist-info/METADATA
ondine-1.3.3.dist-info/WHEEL
ondine-1.3.3.dist-info/entry_points.txt
ondine-1.3.3.dist-info/licenses/LICENSE
ondine-1.3.3.dist-info/RECORD
