Metadata-Version: 2.4
Name: ondine
Version: 1.3.3
Summary: Ondine - The LLM Dataset Engine. SDK for processing tabular datasets using LLMs with reliability, observability, and cost control
Project-URL: Homepage, https://github.com/ptimizeroracle/Ondine
Project-URL: Repository, https://github.com/ptimizeroracle/Ondine
Project-URL: Documentation, https://ptimizeroracle.github.io/ondine
Project-URL: Issues, https://github.com/ptimizeroracle/Ondine/issues
Author-email: Binblok <git@binblok.com>
License: MIT
License-File: LICENSE
Keywords: ai,batch-processing,data-engineering,data-transformation,dataset,llama-index,llm,machine-learning
Classifier: Development Status :: 4 - Beta
Classifier: Intended Audience :: Developers
Classifier: License :: OSI Approved :: MIT License
Classifier: Programming Language :: Python :: 3.10
Classifier: Programming Language :: Python :: 3.11
Classifier: Programming Language :: Python :: 3.12
Classifier: Topic :: Scientific/Engineering :: Artificial Intelligence
Classifier: Topic :: Software Development :: Libraries :: Python Modules
Requires-Python: >=3.10
Requires-Dist: click>=8.1.0
Requires-Dist: jinja2>=3.1.0
Requires-Dist: langfuse>=2.0.0
Requires-Dist: llama-index-llms-anthropic>=0.3.0
Requires-Dist: llama-index-llms-azure-openai>=0.3.0
Requires-Dist: llama-index-llms-groq>=0.3.0
Requires-Dist: llama-index-llms-openai>=0.3.0
Requires-Dist: llama-index>=0.12.0
Requires-Dist: openpyxl>=3.1.0
Requires-Dist: opentelemetry-api>=1.20.0
Requires-Dist: opentelemetry-sdk>=1.20.0
Requires-Dist: pandas>=2.0.0
Requires-Dist: polars>=0.20.0
Requires-Dist: prometheus-client>=0.20.0
Requires-Dist: pyarrow>=15.0.0
Requires-Dist: pydantic>=2.0.0
Requires-Dist: python-dotenv>=1.0.0
Requires-Dist: rich>=13.0.0
Requires-Dist: structlog>=24.0.0
Requires-Dist: tenacity>=8.2.0
Requires-Dist: tiktoken>=0.5.0
Requires-Dist: tqdm>=4.66.0
Provides-Extra: azure
Requires-Dist: azure-identity>=1.15.0; extra == 'azure'
Provides-Extra: dev
Requires-Dist: bandit>=1.7.0; extra == 'dev'
Requires-Dist: interrogate>=1.7.0; extra == 'dev'
Requires-Dist: ipython>=8.20.0; extra == 'dev'
Requires-Dist: jupyter>=1.0.0; extra == 'dev'
Requires-Dist: mypy>=1.13.0; extra == 'dev'
Requires-Dist: pip-audit>=2.7.0; extra == 'dev'
Requires-Dist: pip-licenses>=4.3.0; extra == 'dev'
Requires-Dist: pre-commit>=4.0.0; extra == 'dev'
Requires-Dist: pydocstyle>=6.3.0; extra == 'dev'
Requires-Dist: pytest-asyncio>=0.23.0; extra == 'dev'
Requires-Dist: pytest-cov>=4.1.0; extra == 'dev'
Requires-Dist: pytest>=8.0.0; extra == 'dev'
Requires-Dist: ruff>=0.8.0; extra == 'dev'
Provides-Extra: docs
Requires-Dist: mkdocs-gen-files>=0.5.0; extra == 'docs'
Requires-Dist: mkdocs-literate-nav>=0.6.0; extra == 'docs'
Requires-Dist: mkdocs-material>=9.5.0; extra == 'docs'
Requires-Dist: mkdocs-section-index>=0.3.0; extra == 'docs'
Requires-Dist: mkdocs>=1.5.0; extra == 'docs'
Requires-Dist: mkdocstrings[python]>=0.24.0; extra == 'docs'
Provides-Extra: mlx
Requires-Dist: mlx-lm>=0.28.0; extra == 'mlx'
Requires-Dist: mlx>=0.29.0; extra == 'mlx'
Provides-Extra: observability
Requires-Dist: opentelemetry-api>=1.20.0; extra == 'observability'
Requires-Dist: opentelemetry-exporter-jaeger>=1.20.0; extra == 'observability'
Requires-Dist: opentelemetry-sdk>=1.20.0; extra == 'observability'
